wagtail_snippet_image/__init__.py
wagtail_snippet_image/attributes.py
wagtail_snippet_image/fields.py
wagtail_snippet_image-0.1.4.dist-info/LICENSE
wagtail_snippet_image-0.1.4.dist-info/WHEEL
wagtail_snippet_image-0.1.4.dist-info/METADATA
wagtail_snippet_image-0.1.4.dist-info/RECORD
