Metadata-Version: 2.1
Name: wagtail-snippet-image
Version: 0.1.4
Summary: Creating a snippet images on Wagtail for sharing for social media.
Home-page: https://github.com/acrius/wagtail-snippet-image
License: MIT
Author: acrius
Author-email: acrius@mail.ru
Requires-Python: >=3.5,<4.0
Classifier: License :: OSI Approved :: MIT License
Classifier: Programming Language :: Python :: 3
Classifier: Programming Language :: Python :: 3.5
Classifier: Programming Language :: Python :: 3.6
Classifier: Programming Language :: Python :: 3.7
Requires-Dist: django-snippet-image (>=0.1.3,<0.2.0)
Requires-Dist: wagtail (>=2.5,<3.0)
Project-URL: Repository, https://github.com/acrius/wagtail-snippet-image
